PomidorAPI/__init__.py
pomidor_api_sdk-1.5.0.dist-info/LICENSE
pomidor_api_sdk-1.5.0.dist-info/METADATA
pomidor_api_sdk-1.5.0.dist-info/WHEEL
pomidor_api_sdk-1.5.0.dist-info/top_level.txt
pomidor_api_sdk-1.5.0.dist-info/RECORD
