Metadata-Version: 2.1
Name: pomidor-api-sdk
Version: 1.5.0
Summary: SDK for easy contact with https://api.pomidorproject
Home-page: https://t.me/pomidorik_sus
Author: SuSLiK
Classifier: Programming Language :: Python :: 3.11
Classifier: License :: OSI Approved :: MIT License
Classifier: Operating System :: OS Independent
Requires-Python: >=3.7
License-File: LICENSE
Requires-Dist: requests >=2.25.1
